pydong/__init__.py
pydong/cli.py
pydong/pydong.py
pydong/utils.py
pydong-0.1.3.dist-info/AUTHORS.rst
pydong-0.1.3.dist-info/LICENSE
pydong-0.1.3.dist-info/METADATA
pydong-0.1.3.dist-info/WHEEL
pydong-0.1.3.dist-info/entry_points.txt
pydong-0.1.3.dist-info/top_level.txt
pydong-0.1.3.dist-info/RECORD
